{"lastUsed":1560747368394,"path":"C:\/workspace_script","projectCount":1,"recentFiles":[{"path":"\/dev_html\/WebContent\/js_document","parentWorkspace":"C:\/workspace_script","name":"document_1.html","lastModified":1560478494244,"locationURI":"file:\/C:\/workspace_script\/dev_html\/WebContent\/js_document\/document_1.html"},{"path":"\/dev_html\/WebContent\/css","parentWorkspace":"C:\/workspace_script","name":"bootstrap.min.css","lastModified":1550044070000},{"path":"\/dev_html\/WebContent\/html_iframe","parentWorkspace":"C:\/workspace_script","name":"iFrame_1.html","lastModified":1560224699663},{"path":"\/dev_html\/WebContent\/html_event","parentWorkspace":"C:\/workspace_script","name":"eventStop.html","lastModified":1560742903900,"locationURI":"file:\/C:\/workspace_script\/dev_html\/WebContent\/html_event\/eventStop.html"},{"path":"\/dev_html\/WebContent\/jquery_1","parentWorkspace":"C:\/workspace_script","name":"setInterval_1.html","lastModified":1560744550454,"locationURI":"file:\/C:\/workspace_script\/dev_html\/WebContent\/jquery_1\/setInterval_1.html"},{"path":"\/dev_html\/WebContent\/html_event","parentWorkspace":"C:\/workspace_script","name":"onSubmit_1.html","lastModified":1560740874029,"locationURI":"file:\/C:\/workspace_script\/dev_html\/WebContent\/html_event\/onSubmit_1.html"},{"path":"\/dev_html\/WebContent\/html_day2","parentWorkspace":"C:\/workspace_script","name":"innerHTMLTest.html","lastModified":1560131193599},{"path":"\/dev_html\/WebContent\/html_list","parentWorkspace":"C:\/workspace_script","name":"listTag_1.html","lastModified":1560128879148},{"path":"\/dev_html\/WebContent\/js_object","parentWorkspace":"C:\/workspace_script","name":"sonata.html","lastModified":1560477274384,"locationURI":"file:\/C:\/workspace_script\/dev_html\/WebContent\/js_object\/sonata.html"},{"path":"\/dev_html\/WebContent\/js_array","parentWorkspace":"C:\/workspace_script","name":"arrayObject_2.html","lastModified":1560480952724,"locationURI":"file:\/C:\/workspace_script\/dev_html\/WebContent\/js_array\/arrayObject_2.html"},{"path":"\/dev_html\/WebContent\/html_event","parentWorkspace":"C:\/workspace_script","name":"onClick_1.html","lastModified":1560738687939,"locationURI":"file:\/C:\/workspace_script\/dev_html\/WebContent\/html_event\/onClick_1.html"},{"path":"\/dev_html\/WebContent\/js_array","parentWorkspace":"C:\/workspace_script","name":"arrayObject_1.html","lastModified":1560480303473,"locationURI":"file:\/C:\/workspace_script\/dev_html\/WebContent\/js_array\/arrayObject_1.html"},{"path":"\/dev_html\/WebContent\/css","parentWorkspace":"C:\/workspace_script","name":"bootstrap.css","lastModified":1550044070000},{"path":"\/dev_html\/WebContent\/html_day2","parentWorkspace":"C:\/workspace_script","name":"AnchorTest.html","lastModified":1559707317998},{"path":"\/dev_html\/WebContent\/html_list","parentWorkspace":"C:\/workspace_script","name":"navigationMenu.html","lastModified":1560220827004},{"path":"\/dev_html\/WebContent\/html_dom","parentWorkspace":"C:\/workspace_script","name":"textContent.html","lastModified":1560736389010,"locationURI":"file:\/C:\/workspace_script\/dev_html\/WebContent\/html_dom\/textContent.html"},{"path":"\/dev_html\/WebContent\/html_dom","parentWorkspace":"C:\/workspace_script","name":"dom_1.html","lastModified":1560733087738,"locationURI":"file:\/C:\/workspace_script\/dev_html\/WebContent\/html_dom\/dom_1.html"},{"path":"\/dev_html\/WebContent\/css_selector","parentWorkspace":"C:\/workspace_script","name":"listTag_1.html","lastModified":1560226338327},{"path":"\/dev_html\/WebContent\/html_dom","parentWorkspace":"C:\/workspace_script","name":"dom_attr.html","lastModified":1560735155960,"locationURI":"file:\/C:\/workspace_script\/dev_html\/WebContent\/html_dom\/dom_attr.html"},{"path":"\/dev_html\/WebContent\/html_definition","parentWorkspace":"C:\/workspace_script","name":"definition_1.html","lastModified":1560132165562},{"path":"\/dev_html\/WebContent\/html_day2","parentWorkspace":"C:\/workspace_script","name":"imgTag.html","lastModified":1559707930476},{"path":"\/dev_html\/WebContent\/html_dom","parentWorkspace":"C:\/workspace_script","name":"setInterval_1.html","lastModified":1560738181074,"locationURI":"file:\/C:\/workspace_script\/dev_html\/WebContent\/html_dom\/setInterval_1.html"},{"path":"\/dev_html\/WebContent\/html_event","parentWorkspace":"C:\/workspace_script","name":"eventOrder_1.html","lastModified":1560741327463,"locationURI":"file:\/C:\/workspace_script\/dev_html\/WebContent\/html_event\/eventOrder_1.html"},{"path":"\/dev_html\/WebContent\/css","parentWorkspace":"C:\/workspace_script","name":"bootstrap_1.css","lastModified":1560226891019,"locationURI":"file:\/C:\/workspace_script\/dev_html\/WebContent\/css\/bootstrap_1.css"},{"path":"\/dev_html\/WebContent\/html_type","parentWorkspace":"C:\/workspace_script","name":"addressBook.html","lastModified":1560222652571},{"path":"\/dev_html\/WebContent\/jquery_1","parentWorkspace":"C:\/workspace_script","name":"cssTest.html","lastModified":1560745018108,"locationURI":"file:\/C:\/workspace_script\/dev_html\/WebContent\/jquery_1\/cssTest.html"},{"path":"\/Servers\/Tomcat v9.0 Server at localhost-config","parentWorkspace":"C:\/workspace_script","name":"server.xml","lastModified":1559706514998},{"path":"\/dev_html\/WebContent\/html_event","parentWorkspace":"C:\/workspace_script","name":"test.jsp","lastModified":1560737900611,"locationURI":"file:\/C:\/workspace_script\/dev_html\/WebContent\/html_event\/test.jsp"},{"path":"\/dev_html\/WebContent\/html_table","parentWorkspace":"C:\/workspace_script","name":"table_1.html","lastModified":1560133420319},{"path":"\/dev_html\/WebContent\/html_table","parentWorkspace":"C:\/workspace_script","name":"loginAction.html","lastModified":1560139766129},{"path":"\/dev_html\/WebContent\/js_object","parentWorkspace":"C:\/workspace_script","name":"loginForm.html","lastModified":1560478480898,"locationURI":"file:\/C:\/workspace_script\/dev_html\/WebContent\/js_object\/loginForm.html"},{"path":"\/dev_html\/WebContent\/css","parentWorkspace":"C:\/workspace_script","name":"bootstrap-grid.css","lastModified":1550044070000},{"path":"\/dev_html\/WebContent\/html_list","parentWorkspace":"C:\/workspace_script","name":"listTag_1a.html","lastModified":1560129401359},{"path":"\/dev_html\/WebContent\/html_semantic","parentWorkspace":"C:\/workspace_script","name":"beforeSemantic.html","lastModified":1560131292421}]}